UniversalApplicationAssembler/__init__.py
UniversalApplicationAssembler/compiler.py
UniversalApplicationAssembler/parser.py
UniversalApplicationAssembler/helpers/__init__.py
UniversalApplicationAssembler/helpers/classes.py
UniversalApplicationAssembler/helpers/functions.py
pyuaa-0.1.1.dist-info/licenses/LICENSE
pyuaa-0.1.1.dist-info/METADATA
pyuaa-0.1.1.dist-info/WHEEL
pyuaa-0.1.1.dist-info/top_level.txt
pyuaa-0.1.1.dist-info/RECORD
