Metadata-Version: 2.4
Name: PyUAA
Version: 0.1.1
Summary: Create easily custom assemblers specifying ISAs with a YAML configuration file
Author-email: SpaceProgrammer <spaceprogrammerbusiness@gmail.com>
License-Expression: LicenseRef-Voltionne-Restrictive
Project-URL: Repository, https://github.com/Voltionne/UniversalApplicationAssembler
Keywords: assembler,compiler
Classifier: Programming Language :: Python :: 3
Classifier: Operating System :: OS Independent
Requires-Python: >=3.9
License-File: LICENSE
Requires-Dist: pyyaml
Dynamic: license-file
